contablibi/__init__.py
contablibi/calcular_balanco.py
contablibi/calcular_rescisao.py
contablibi/exportar_pdf.py
contablibi/grafico.py
contablibi/registrar_transacao.py
Contablibi-0.0.9.dist-info/METADATA
Contablibi-0.0.9.dist-info/WHEEL
Contablibi-0.0.9.dist-info/top_level.txt
Contablibi-0.0.9.dist-info/RECORD
